README.md
setup.py
taobaopy/__init__.py
taobaopy/taobao.py
taobaopy6.egg-info/PKG-INFO
taobaopy6.egg-info/SOURCES.txt
taobaopy6.egg-info/dependency_links.txt
taobaopy6.egg-info/not-zip-safe
taobaopy6.egg-info/requires.txt
taobaopy6.egg-info/top_level.txt