Metadata-Version: 1.1
Name: taobaopy6
Version: 1.0.1
Summary: A Very Easy Learned Python SDK For TaoBao.com API Support python2 and python3
Home-page: https://github.com/sempr/taobaopy6
Author: Fred Wang
Author-email: taobao-pysdk@1e20.com
License: BSD
Platform: any
Classifier: Development Status :: 5 - Production/Stable
Classifier: Intended Audience :: Developers
Classifier: License :: OSI Approved :: BSD License
Classifier: Programming Language :: Python
Classifier: Topic :: Software Development :: Libraries :: Python Modules
